doWellOpensourceLicenseCompatibility/__init__.py
doWellOpensourceLicenseCompatibility/doWellOpensourceLicenseCompatibility.py
Opensource_License_Compatibility_from_DoWell-0.3.0.dist-info/METADATA
Opensource_License_Compatibility_from_DoWell-0.3.0.dist-info/WHEEL
Opensource_License_Compatibility_from_DoWell-0.3.0.dist-info/top_level.txt
Opensource_License_Compatibility_from_DoWell-0.3.0.dist-info/RECORD
