Metadata-Version: 2.1
Name: Opensource-License-Compatibility-from-DoWell
Version: 0.3.0
Summary: Opensource License Compatibility from DoWell
Author: DoWell UX Living Lab
License: Apache License 2.0
Requires-Dist: requests
